hashtag/__init__.py
hashtag/admin.py
hashtag/apps.py
hashtag/models.py
hashtag/signals.py
hashtag/locale/it/LC_MESSAGES/django.po
hashtag/migrations/0001_initial.py
hashtag/migrations/0002_alter_mytag_slug.py
hashtag/migrations/0003_alter_mytag_last_used.py
hashtag/migrations/0004_alter_mytaggeditem_content_type_and_more.py
hashtag/migrations/__init__.py
django_hashtag-0.2.1.dist-info/LICENSE
django_hashtag-0.2.1.dist-info/METADATA
django_hashtag-0.2.1.dist-info/WHEEL
django_hashtag-0.2.1.dist-info/top_level.txt
django_hashtag-0.2.1.dist-info/RECORD
